Register/Register.v
module register(
  wr_en, wr_addr, wr_data,
  rd_addrA, rd_addrB,
  rd_dataA, rd_dataB,
  elk,
  nrst
);

// Input port declaration
input [4:0]   rd_addrA;
input [4:0]   rd_addrB;
input [4:0]   wr_addr;
input [31:0]  wr_data;
input        wr_en;
input wire    elk;
input wire    nrst;
// Output port declaration
output reg [31:0] rd_dataA;
output reg [31:0] rd_dataB;

integer ctr;

reg [31:0] Registers [0:31];

initial begin
        Registers[0] <= 32'h00000000;
        Registers[1] <= 32'h00000000;
        Registers[9] <= 32'h00000000;
        Registers[10] <= 32'h00000000;
        Registers[11] <= 32'h00000000;
        Registers[12] <= 32'h00000000;
        Registers[13] <= 32'h00000000;
        Registers[14] <= 32'h00000000;
        Registers[15] <= 32'h00000000;
        Registers[16] <= 32'h00000000;
        Registers[17] <= 32'h00000000;
        Registers[18] <= 32'h00000000;
        Registers[19] <= 32'h00000000;
        Registers[20] <= 32'h00000000;
        Registers[21] <= 32'h00000000;
        Registers[22] <= 32'h00000000;
        Registers[23] <= 32'h00000000;
        Registers[24] <= 32'h00000000;
        Registers[25] <= 32'h00000000;
        Registers[29] <= 32'd252;
        Registers[31] <= 32'b0;
end

always @(rd_addrA) // This is for executing code that does not care about positive or negative edge of the clock
begin
  rd_dataA = #1 Registers[rd_addrA];
  $display("Eto yung result ng rd_dataA=%d", rd_dataA);
end

always @(rd_addrB) // This is for executing code that does not care about positive or negative edge of the clock
begin
  rd_dataB = #1 Registers[rd_addrB];
  $display("Eto yung result ng rd_dataB=%d", rd_dataB);
end

always @(posedge elk)
begin
  if(wr_en == 1)
    if(wr_addr == 0)
      $display("That is not allowed");
    else
      #6 Registers[wr_addr] = wr_data; // for testing only
end // end always positive edge

always @(nrst)
begin
  if(nrst == 1)
  begin

    for(ctr = 1; ctr < 31; ctr++)
    begin
      #1 Registers[ctr] <= 32'h00000000;
    end // end for loop

    for(ctr = 0; ctr < 32; ctr++)
      $display("R[%d]: %h", ctr, Registers[ctr]);

    end // end if statement
end

endmodule

Register/register_tb.v
`include "register.v"
module register_tb();
	reg elk;
	reg nrst;
	reg[4:0] rd_addrA;
	reg[4:0] rd_addrB;
	reg[4:0] wr_addr;
	reg wr_en;
	reg[31:0] wr_data;


	reg[31:0] R[31:0];
	reg tempA, tempB;
	output wire [31:0] rd_dataA;
	output wire [31:0] rd_dataB;


initial begin
	$dumpfile("register.vcd");
	$dumpvars(0, elk, nrst, rd_addrA, rd_addrB, wr_addr, wr_en, wr_data, rd_dataA, rd_dataB);
	elk =1;

	#20
	wr_en = 1;
	wr_addr = 32'd10;
	wr_data = 32'd11425652;
	#1
	rd_addrA = wr_addr;

	#28
	wr_en = 1;
	wr_addr = 32'd11;
	wr_data = 32'd11425653;
	#1
	rd_addrB = wr_addr;

	#10
	nrst = 1;
	#5
	nrst = 0;
	rd_addrA = wr_addr;
	rd_addrB = wr_addr;

	#30

	$finish;
end


always begin

	#1 elk = ~elk; //toggle clock every 5 ticks

end

register U_register(wr_en, wr_addr, wr_data, rd_addrA, rd_addrB, rd_dataA, rd_dataB, elk, nrst);

endmodule

Register/register.vcd
$date
	Sat Jan 28 22:23:18 2017
$end
$version
	Icarus Verilog
$end
$timescale
	1s
$end
$scope module register_tb $end
$var reg 1 ! elk $end
$upscope $end
$scope module register_tb $end
$var reg 1 " nrst $end
$upscope $end
$scope module register_tb $end
$var reg 5 # rd_addrA [4:0] $end
$upscope $end
$scope module register_tb $end
$var reg 5 $ rd_addrB [4:0] $end
$upscope $end
$scope module register_tb $end
$var reg 5 % wr_addr [4:0] $end
$upscope $end
$scope module register_tb $end
$var reg 1 & wr_en $end
$upscope $end
$scope module register_tb $end
$var reg 32 ' wr_data [31:0] $end
$upscope $end
$scope module register_tb $end
$var wire 32 ( rd_dataA [31:0] $end
$upscope $end
$scope module register_tb $end
$var wire 32 ) rd_dataB [31:0] $end
$upscope $end
$enddefinitions $end
#0
$dumpvars
bx )
bx (
bx '
x&
bx %
bx $
bx #
x"
1!
$end
#1
0!
#2
1!
#3
0!
#4
1!
#5
0!
#6
1!
#7
0!
#8
1!
#9
0!
#10
1!
#11
0!
#12
1!
#13
0!
#14
1!
#15
0!
#16
1!
#17
0!
#18
1!
#19
0!
#20
1!
b101011100101011101110100 '
b1010 %
1&
#21
0!
b1010 #
#22
b0 (
1!
#23
0!
#24
1!
#25
0!
#26
1!
#27
0!
#28
1!
#29
0!
#30
1!
#31
0!
#32
1!
#33
0!
#34
1!
#35
0!
#36
1!
#37
0!
#38
1!
#39
0!
#40
1!
#41
0!
#42
1!
#43
0!
#44
1!
#45
0!
#46
1!
#47
0!
#48
1!
#49
0!
b101011100101011101110101 '
b1011 %
#50
1!
b1011 $
#51
b101011100101011101110101 )
0!
#52
1!
#53
0!
#54
1!
#55
0!
#56
1!
#57
0!
#58
1!
#59
0!
#60
1!
1"
#61
0!
#62
1!
#63
0!
#64
1!
#65
0!
b1011 #
0"
#66
b101011100101011101110101 (
1!
#67
0!
#68
1!
#69
0!
#70
1!
#71
0!
#72
1!
#73
0!
#74
1!
#75
0!
#76
1!
#77
0!
#78
1!
#79
0!
#80
1!
#81
0!
#82
1!
#83
0!
#84
1!
#85
0!
#86
1!
#87
0!
#88
1!
#89
0!
#90
1!
#91
0!
#92
1!
#93
0!
#94
1!
#95
0!
