Register.v
module register(
  wr_en, wr_addr, wr_data,
  rd_addrA, rd_addrB,
  rd_dataA, rd_dataB,
  elk,
  nrst
);

// Input port declaration
input [4:0]   rd_addrA;
input [4:0]   rd_addrB;
input [4:0]   wr_addr;
input [31:0]  wr_data;
input        wr_en;
input wire    elk;
input wire    nrst;
// Output port declaration
output     [31:0] rd_dataA;
output      [31:0] rd_dataB;

integer ctr;

reg [31:0] Registers [0:31];

initial begin
        Registers[0] <= 32'h00000000;
        Registers[8] <= 32'h00000000;
        Registers[9] <= 32'h00000000;
        Registers[10] <= 32'h00000000;
        Registers[11] <= 32'h00000000;
        Registers[12] <= 32'h00000000;
        Registers[13] <= 32'h00000000;
        Registers[14] <= 32'h00000000;
        Registers[15] <= 32'h00000000;
        Registers[16] <= 32'h00000000;
        Registers[17] <= 32'h00000000;
        Registers[18] <= 32'h00000000;
        Registers[19] <= 32'h00000000;
        Registers[20] <= 32'h00000000;
        Registers[21] <= 32'h00000000;
        Registers[22] <= 32'h00000000;
        Registers[23] <= 32'h00000000;
        Registers[24] <= 32'h00000000;
        Registers[25] <= 32'h00000000;
        Registers[29] <= 32'd252;
        Registers[31] <= 32'b0;
end

always @(*) // This is for executing code that does not care about positive or negative edge of the clock
begin
  Registers[rd_addrA] = rd_dataA;
  Registers[rd_addrB] = rd_dataB;
  $display("rd_addrA=$h", rd_addrA);
  $display("rd_addrB=$h", rd_addrB);
end

always @(posedge elk)
begin
  if(wr_en == 1)
    Registers[wr_addr] = wr_data; // for testing only

  if(nrst == 1)
  begin
    
    for(ctr = 1; ctr < 32; ctr++)
    begin
      Registers[ctr] <= 32'h00000000;
    end // end for loop

  end // end if statement

end // end always positive edge

endmodule

register_tb.v
//`timescale 1ns/100ps
`include "register.v"

module register_tb();

	reg [4:0]  wr_addr = 0;
	reg [4:0]  rd_addrA = 0;
	reg [4:0]  rd_addrB = 0;
	reg elk, nrst, wr_en;
	
	wire [31:0] wr_data, rd_dataA, rd_dataB;

	integer ctr;

	// assign all wires here
	assign {wr_data, rd_dataA, rd_dataB} = 0;

	// Main Function
	initial begin
		$dumpfile("register.vcd");
		$dumpvars(0, register_tb);
		elk = 1; // clock started at 1

		for(ctr = 0; ctr < 25; ctr++)
		begin
			#1 
			rd_addrA = rd_addrA + 1;
			$display("Counter: %d", ctr);
			$display("Read Address A: %0h", rd_addrA);
			
			#10
			nrst = 1;
		end

		$finish;
	end

	// Clock Ticking Function
	always begin
		#5 elk = ~elk;
	end

	register reg_file(wr_en, wr_addr, wr_data, rd_addrA, 
		rd_addrB, rd_dataA, rd_dataB, elk, nrst);

endmodule

register.vcd
$date
	Fri Jan 27 18:27:40 2017
$end
$version
	Icarus Verilog
$end
$timescale
	1s
$end
$scope module register_tb $end
$var wire 32 ! wr_data [31:0] $end
$var wire 32 " rd_dataB [31:0] $end
$var wire 32 # rd_dataA [31:0] $end
$var reg 1 $ elk $end
$var reg 1 % nrst $end
$var reg 5 & rd_addrA [4:0] $end
$var reg 5 ' rd_addrB [4:0] $end
$var reg 5 ( wr_addr [4:0] $end
$var reg 1 ) wr_en $end
$var integer 32 * ctr [31:0] $end
$scope module reg_file $end
$var wire 1 $ elk $end
$var wire 1 % nrst $end
$var wire 5 + rd_addrA [4:0] $end
$var wire 5 , rd_addrB [4:0] $end
$var wire 32 - rd_dataA [31:0] $end
$var wire 32 . rd_dataB [31:0] $end
$var wire 5 / wr_addr [4:0] $end
$var wire 32 0 wr_data [31:0] $end
$var wire 1 ) wr_en $end
$var integer 32 1 ctr [31:0] $end
$upscope $end
$upscope $end
$enddefinitions $end
#0
$dumpvars
bx 1
b0 0
b0 /
b0 .
b0 -
b0 ,
b0 +
b0 *
x)
b0 (
b0 '
b0 &
x%
1$
b0 #
b0 "
b0 !
$end
#1
b1 &
b1 +
#5
0$
#10
1$
#11
b1 *
1%
#12
b10 &
b10 +
#15
0$
#20
b100000 1
1$
#22
b10 *
#23
b11 &
b11 +
#25
0$
#30
b100000 1
1$
#33
b11 *
#34
b100 &
b100 +
#35
0$
#40
b100000 1
1$
#44
b100 *
#45
b101 &
b101 +
0$
#50
b100000 1
1$
#55
0$
b101 *
#56
b110 &
b110 +
#60
b100000 1
1$
#65
0$
#66
b110 *
#67
b111 &
b111 +
#70
b100000 1
1$
#75
0$
#77
b111 *
#78
b1000 &
b1000 +
#80
b100000 1
1$
#85
0$
#88
b1000 *
#89
b1001 &
b1001 +
#90
b100000 1
1$
#95
0$
#99
b1001 *
#100
b100000 1
b1010 &
b1010 +
1$
#105
0$
#110
b100000 1
1$
b1010 *
#111
b1011 &
b1011 +
#115
0$
#120
b100000 1
1$
#121
b1011 *
#122
b1100 &
b1100 +
#125
0$
#130
b100000 1
1$
#132
b1100 *
#133
b1101 &
b1101 +
#135
0$
#140
b100000 1
1$
#143
b1101 *
#144
b1110 &
b1110 +
#145
0$
#150
b100000 1
1$
#154
b1110 *
#155
b1111 &
b1111 +
0$
#160
b100000 1
1$
#165
0$
b1111 *
#166
b10000 &
b10000 +
#170
b100000 1
1$
#175
0$
#176
b10000 *
#177
b10001 &
b10001 +
#180
b100000 1
1$
#185
0$
#187
b10001 *
#188
b10010 &
b10010 +
#190
b100000 1
1$
#195
0$
#198
b10010 *
#199
b10011 &
b10011 +
#200
b100000 1
1$
#205
0$
#209
b10011 *
#210
b100000 1
b10100 &
b10100 +
1$
#215
0$
#220
b100000 1
1$
b10100 *
#221
b10101 &
b10101 +
#225
0$
#230
b100000 1
1$
#231
b10101 *
#232
b10110 &
b10110 +
#235
0$
#240
b100000 1
1$
#242
b10110 *
#243
b10111 &
b10111 +
#245
0$
#250
b100000 1
1$
#253
b10111 *
#254
b11000 &
b11000 +
#255
0$
#260
b100000 1
1$
#264
b11000 *
#265
b11001 &
b11001 +
0$
#270
b100000 1
1$
#275
0$
b11001 *
