Register.v
module register(
  wr_en, wr_addr, wr_data,
  rd_addrA, rd_addrB,
  rd_dataA, rd_dataB,
  elk,
  nrst
);

// Input port declaration
input [4:0]   rd_addrA;
input [4:0]   rd_addrB;
input [4:0]   wr_addr;
input [31:0]  wr_data;
input        wr_en;
input wire    elk;
input wire    nrst;
// Output port declaration
output reg [31:0] rd_dataA;
output reg [31:0] rd_dataB;

integer ctr;

reg [31:0] Registers [0:31];

initial begin
        Registers[0] <= 32'h00000000;
        Registers[1] <= 32'h11111110;
        Registers[9] <= 32'h00000000;
        Registers[10] <= 32'h00000000;
        Registers[11] <= 32'h00000000;
        Registers[12] <= 32'h00000000;
        Registers[13] <= 32'h00000000;
        Registers[14] <= 32'h00000000;
        Registers[15] <= 32'h00000000;
        Registers[16] <= 32'h00000000;
        Registers[17] <= 32'h00000000;
        Registers[18] <= 32'h00000000;
        Registers[19] <= 32'h00000000;
        Registers[20] <= 32'h00000000;
        Registers[21] <= 32'h00000000;
        Registers[22] <= 32'h00000000;
        Registers[23] <= 32'h00000000;
        Registers[24] <= 32'h00000000;
        Registers[25] <= 32'h00000000;
        Registers[29] <= 32'd252;
        Registers[31] <= 32'b0;
end

always @(rd_addrA) // This is for executing code that does not care about positive or negative edge of the clock
begin
  rd_dataA = #1 Registers[rd_addrA];
  $display("Eto yung result ng rd_dataA=%h", rd_dataA);
end

always @(rd_addrB) // This is for executing code that does not care about positive or negative edge of the clock
begin
  rd_dataB = #1 Registers[rd_addrB];
  $display("Eto yung result ng rd_dataB=%h", rd_dataB);
end

always @(posedge elk)
begin
  if(wr_en == 1)
    Registers[wr_addr] = wr_data; // for testing only

  if(nrst == 1)
  begin

    for(ctr = 1; ctr < 32; ctr++)
    begin
      Registers[ctr] <= 32'h00000000;
    end // end for loop

    for(ctr = 1; ctr < 5; ctr++)
      $display("R[%d]: %h", ctr, Registers[ctr]);

  end // end if statement

end // end always positive edge

endmodule

register_tb.v
//`timescale 1ns/100ps
`include "Register.v"

/*
Test Process: (only modify R1-R4 registers)

> Registers that are associated with rd_addrA:
R1, R2

> Registers that are associated with rd_addrB:
R3, R4

> At start of program these are the values:
R1 = 11111110;
R2 = 22222220;
R3 = 33333330;
R4 = 44444440;

> Every 2 seconds, the values of all registers increase by 1

> Every 10 seconds, all reg values will reset via nrst variable

> program should run for 30 seconds

*/

module register_tb();

	reg [4:0]  wr_addr = 0;
	reg [4:0]  rd_addrA = 0;
	reg [4:0]  rd_addrB = 0;
	reg elk, nrst, wr_en;
	reg [31:0] Registers [0:31];
	
	wire [31:0] wr_data, rd_dataA, rd_dataB;

	integer prog_ctr, reg_ctr;

	// assign all wires here
	assign {wr_data, rd_dataA, rd_dataB} = 0;

	// Main Function
	initial begin
		$dumpfile("register.vcd");
		$dumpvars(0, register_tb);

		Registers[1] = 32'h11111110;
		Registers[2] = 32'h22222220;
		Registers[3] = 32'h33333330;
		Registers[4] = 32'h44444440;

		for(prog_ctr = 1; prog_ctr <= 4; prog_ctr++)
			$display("R[%d]: %h", prog_ctr, Registers[prog_ctr]);

		$display("End of initialization"); // ~debugging~
		
		for(prog_ctr = 0; prog_ctr < 20; prog_ctr++)
		begin
			#2 
			// add all reg values by 1
			$display("Counter: %d", prog_ctr);
			for(reg_ctr = 1; reg_ctr < 5; reg_ctr++)
			begin
				rd_addrA = reg_ctr; // if assigned
				Registers[rd_addrA] = Registers[rd_addrA] + 1; // if used
			end

			#10
			elk = 1;
			nrst = 0;
		end
		
		$finish;
	end

	// Clock Ticking Function
	always begin
		#5 elk = ~elk;
	end

	register reg_file(wr_en, wr_addr, wr_data, rd_addrA, 
		rd_addrB, rd_dataA, rd_dataB, elk, nrst);

endmodule

register.vcd
$date
	Fri Jan 27 23:06:16 2017
$end
$version
	Icarus Verilog
$end
$timescale
	1s
$end
$scope module register_tb $end
$var wire 32 ! rd_dataA [31:0] $end
$var wire 32 " rd_dataB [31:0] $end
$var wire 32 # wr_data [31:0] $end
$var reg 1 $ elk $end
$var reg 1 % nrst $end
$var reg 5 & rd_addrA [4:0] $end
$var reg 5 ' rd_addrB [4:0] $end
$var reg 5 ( wr_addr [4:0] $end
$var reg 1 ) wr_en $end
$var integer 32 * prog_ctr [31:0] $end
$var integer 32 + reg_ctr [31:0] $end
$scope module reg_file $end
$var wire 1 $ elk $end
$var wire 1 % nrst $end
$var wire 5 , rd_addrA [4:0] $end
$var wire 5 - rd_addrB [4:0] $end
$var wire 5 . wr_addr [4:0] $end
$var wire 32 / wr_data [31:0] $end
$var wire 1 ) wr_en $end
$var reg 32 0 rd_dataA [31:0] $end
$var reg 32 1 rd_dataB [31:0] $end
$var integer 32 2 ctr [31:0] $end
$upscope $end
$upscope $end
$enddefinitions $end
#0
$dumpvars
bx 2
bx 1
bx 0
b0 /
b0 .
b0 -
b0 ,
bx +
b0 *
x)
b0 (
b0 '
b0 &
x%
x$
b0 #
bx "
bx !
$end
#2
b100 &
b100 ,
b101 +
#12
b1 *
0%
1$
#14
b100 &
b100 ,
b101 +
#15
0$
#20
1$
#24
b10 *
#25
0$
#26
b100 &
b100 ,
b101 +
#30
1$
#35
0$
#36
b11 *
1$
#38
b100 &
b100 ,
b101 +
#40
0$
#45
1$
#48
b100 *
#50
b100 &
b100 ,
b101 +
0$
#55
1$
#60
0$
b101 *
#62
b100 &
b100 ,
b101 +
#65
1$
#70
0$
#72
b110 *
1$
#74
b100 &
b100 ,
b101 +
#75
0$
#80
1$
#84
b111 *
#85
0$
#86
b100 &
b100 ,
b101 +
#90
1$
#95
0$
#96
b1000 *
1$
#98
b100 &
b100 ,
b101 +
#100
0$
#105
1$
#108
b1001 *
#110
b100 &
b100 ,
b101 +
0$
#115
1$
#120
0$
b1010 *
#122
b100 &
b100 ,
b101 +
#125
1$
#130
0$
#132
b1011 *
1$
#134
b100 &
b100 ,
b101 +
#135
0$
#140
1$
#144
b1100 *
#145
0$
#146
b100 &
b100 ,
b101 +
#150
1$
#155
0$
#156
b1101 *
1$
#158
b100 &
b100 ,
b101 +
#160
0$
#165
1$
#168
b1110 *
#170
b100 &
b100 ,
b101 +
0$
#175
1$
#180
0$
b1111 *
#182
b100 &
b100 ,
b101 +
#185
1$
#190
0$
#192
b10000 *
1$
#194
b100 &
b100 ,
b101 +
#195
0$
#200
1$
#204
b10001 *
#205
0$
#206
b100 &
b100 ,
b101 +
#210
1$
#215
0$
#216
b10010 *
1$
#218
b100 &
b100 ,
b101 +
#220
0$
#225
1$
#228
b10011 *
#230
b100 &
b100 ,
b101 +
0$
#235
1$
#240
0$
b10100 *
