Samples/full_adder.v
module full_adder(
clock,
a, b, cin,
sum, cout
);

// Variable Declarations
input wire a, b, cin, clock;
output reg sum, cout;

always @ (posedge clock)
begin : Full_Adder
	sum  = #1 a ^ b ^ cin;
	cout = #1 (a & b) | (cin & a) | (cin & b);
end

endmodule

Samples/full_adder_tb.v
`include "full_adder.v"

module full_adder_tb();

reg a, b, cin, clock;
wire sum, cout;

initial begin
  $dumpfile("full_adder.vcd"); 
  $dumpvars(0,a,b,cin,sum,cout,clock);
  clock = 1;
  #5
  a = 1'b1;
  b = 1'b0;
  cin = 1'b0;
  // sum = 1
  // cout = 0
  #10
  a = 1'b1;
  b = 1'b0;
  cin = 1'b1;
  // sum = 0
  // cout = 1
  #10
  a = 1'b1;
  b = 1'b1;
  cin = 1'b1; 
  // sum =1
  // cout =1
  #10
  a = 1'b0;
  b = 1'b1;
  cin = 1'b1;  
  // sum = 0
  // cout = 1
  #10
  $finish;
end

// Clock generator
always begin
  #5 clock = ~clock; // Toggle clock every 5 ticks
end

// Connect DUT to test bench
full_adder U_full_adder (
clock,
a, b, cin,
sum, cout
);

endmodule

Samples/full_adder.vcd
$date
	Tue Jan 17 14:10:31 2017
$end
$version
	Icarus Verilog
$end
$timescale
	1s
$end
$scope module full_adder_tb $end
$var reg 1 ! a $end
$upscope $end
$scope module full_adder_tb $end
$var reg 1 " b $end
$upscope $end
$scope module full_adder_tb $end
$var reg 1 # cin $end
$upscope $end
$scope module full_adder_tb $end
$var wire 1 $ sum $end
$upscope $end
$scope module full_adder_tb $end
$var wire 1 % cout $end
$upscope $end
$scope module full_adder_tb $end
$var reg 1 & clock $end
$upscope $end
$enddefinitions $end
#0
$dumpvars
1&
x%
x$
x#
x"
x!
$end
#5
0&
0#
0"
1!
#10
1&
#11
1$
#12
0%
#15
0&
1#
#20
1&
#21
0$
#22
1%
#25
0&
1"
#30
1&
#31
1$
#35
0&
0!
#40
1&
#41
0$
