ALU/alu.v
module alu(
	opA, opB,
	sel,
	res,
	z, c, v
);

	input [31:0] opA;
	input [31:0] opB;
	input [2:0] sel;
	output reg [31:0] res;
	output reg z, c, v;

	integer ctr;

	initial begin
	end

	always @(*) begin

		z = 0;
		c = 0;
		v = 0;
		res = 32'h00000000;
		// Addition
		if(sel == 3'b000) begin
			{c, res} = opA + opB;
			$display("%b", res);
			if(res == 32'h00000000)
				z = 1;
			if((opA[31] == opB[31]) && res[31] == ~opA[31])
				v = 1;
		end
		// Subtraction
		else if(sel == 3'b001) begin
			{c, res} = opA - opB;
			$display("%b", res);
			if(res == 32'h00000000)
				z = 1;
			if((~opA[31] == opB[31]) && res[31] == ~opA[31])
				v = 1;
		end
		else if(sel == 3'b010) begin
			res = opA & opB;
			$display("%b", res);
			if(res == 32'h00000000)
				z = 1;
		end
		else if(sel == 3'b011) begin
			res = opA | opB;
			$display("%b", res);
			if(res == 32'h00000000)
				z = 1;
		end
		else if(sel == 3'b100) begin
			res = ~opA;
			$display("%b", res);
			if(res == 32'h00000000)
				z = 1;
		end
		else begin
			$display("Invalid 'sel' value");
		end

		$display("Zero Flag: %b", z);
		$display("Carry Flag: %b", c);
		$display("Overflow Flag: %b", v);
	end

endmodule

ALU/alu_tb.v
`include "alu.v"
module alu_tb();
	reg[31:0] opA;
	reg[31:0] opB;
	reg[2:0] sel;

	wire[31:0] res;
	wire z;
	wire c;
	wire v;

initial begin
	$dumpfile("alu.vcd");
	$dumpvars(0, opA, opB, sel, res, z, c, v);


	#5
	sel = 3'b000;
	opA = 32'h8FFFFFFF;
	opB = 32'h8FFFFFFF;

	#5
	sel = 3'b001;
	opA = 32'h0FFFFFFF;
	opB = 32'h8FFFFFFF;

	#5
	sel = 3'b000;
	opA = 32'hFFFFFFFF;
	opB = 32'h00000004;

	#5
	sel = 3'b010;
	opA = 32'hFFFFFFFF;
	opB = 32'h55555555;

	#5
	sel = 3'b000;
	opA = 32'h40000000;
	opB = 32'h40000000;

	#5
	sel = 3'b000;
	opA = 32'h00000000;
	opB = 32'h00000000;

	#5
	sel = 3'b001;
	opA = 32'h80000000;
	opB = 32'h70000000;

	#5
	sel = 3'b001;
	opA = 32'h00000000;
	opB = 32'hffffffff;

	#5
	sel = 3'b001;
	opA = 32'h00000006;
	opB = 32'h00000001;

	#5
	sel = 3'b001;
	opA = 32'h00000001;
	opB = 32'h00000001;

	#5
	sel = 3'b001;
	opA = 32'h00000000;
	opB = 32'h00000001;

	#5
	sel = 3'b110;
	opA = 32'h00000000;
	opB = 32'h00000001;

	#20

	$finish;
end


alu U_alu(opA, opB, sel, res, z, c, v);

endmodule

ALU/alu.vcd
$date
	Sat Jan 28 23:35:57 2017
$end
$version
	Icarus Verilog
$end
$timescale
	1s
$end
$scope module alu_tb $end
$var reg 32 ! opA [31:0] $end
$upscope $end
$scope module alu_tb $end
$var reg 32 " opB [31:0] $end
$upscope $end
$scope module alu_tb $end
$var reg 3 # sel [2:0] $end
$upscope $end
$scope module alu_tb $end
$var wire 32 $ res [31:0] $end
$upscope $end
$scope module alu_tb $end
$var wire 1 % z $end
$upscope $end
$scope module alu_tb $end
$var wire 1 & c $end
$upscope $end
$scope module alu_tb $end
$var wire 1 ' v $end
$upscope $end
$enddefinitions $end
#0
$dumpvars
x'
x&
x%
bx $
bx #
bx "
bx !
$end
#5
b11111111111111111111111111110 $
1'
1&
0%
b10001111111111111111111111111111 "
b10001111111111111111111111111111 !
b0 #
#10
b10000000000000000000000000000000 $
1'
1&
b1111111111111111111111111111 !
b1 #
#15
b11 $
0'
1&
b100 "
b11111111111111111111111111111111 !
b0 #
#20
b1010101010101010101010101010101 $
0&
b1010101010101010101010101010101 "
b10 #
#25
1'
b10000000000000000000000000000000 $
b1000000000000000000000000000000 "
b1000000000000000000000000000000 !
b0 #
#30
1%
b0 $
0'
b0 "
b0 !
#35
1'
b10000000000000000000000000000 $
0%
b1110000000000000000000000000000 "
b10000000000000000000000000000000 !
b1 #
#40
1&
b1 $
0'
b11111111111111111111111111111111 "
b0 !
#45
b101 $
0&
b1 "
b110 !
#50
1%
b0 $
b1 !
#55
1&
b11111111111111111111111111111111 $
0%
b0 !
#60
b0 $
0&
b110 #
